multi_sel.v
`timescale 1ns/1ns
module multi_sel(
input [7:0] d,
input clk,
input rst,
output reg input_grant,
output reg [10:0] out
);
//*************code***********//

wire [3:0] times[3:0];
assign times[0] = 4'd1;
assign times[1] = 4'd3;
assign times[2] = 4'd7;
assign times[3] = 4'd8;

reg [7:0] data;
reg [2:0] i;

// 更新乘数，存储数据 d
always @ (posedge clk or negedge rst) begin
  if (~rst) begin
    out <= 1'b0;
    i <= 3'd0;
  end
  else begin
    if (i >= 3'd3) begin
      i <= 3'd0;
      data <= d;
    end
    else begin
      i <= i + 3'd1;
    end
  end
end

// 更新 input_grant
always @ (posedge clk or negedge rst) begin
  if (~rst) begin
    input_grant <= 1'b0;
  end
  else begin
    if (i == 3'd0) begin
      input_grant <= 1'b1;
    end
    else begin
      input_grant <= 1'b0;
    end
  end
end

// 更新 out
always @ (posedge clk or negedge rst) begin
  if (~rst) begin
    input_grant <= 1'b0;
    out <= 1'b0;
    i <= 3'd0;
  end
  else begin
    case (i)
      3'd0: begin
        out <= d;
        data <= d;
      end
      3'd1: begin
        out <= data * times[i];
      end
      3'd2: begin
        out <= data * times[i];
      end
      3'd3: begin
        out <= data * times[i];
      end
      default: out <= d * times[i];
    endcase
  end
end

//*************code***********//
endmodule

multi_sel_tb.v
`include "./multi_sel.v"

`timescale 1ns/1ns

module testbench();
  reg clk = 0;
  always #5 clk = ~clk;

  reg [7:0] d;
  reg rst;
  wire input_grant;
  wire [10:0] out;

  initial begin
    rst <= 1'b0;
    #10
    rst <= 1'b1;
    #10
    d <= 8'd143;
    #55
    d <= 8'd7;
    #50
    d <= 8'd6;
    #10
    d <= 8'd128;
    #10
    d <= 8'd129;
    #50
    $finish;
  end

  multi_sel m1(
    .d(d),
    .clk(clk),
    .rst(rst),
    .input_grant(input_grant),
    .out(out)
  );
  
  initial begin
    $dumpfile("out.vcd");
    // This will dump all signal, which may not be useful
    //$dumpvars;
    // dumping only this module
    //$dumpvars(1, testbench);
    // dumping only these variable
    // the first number (level) is actually useless
    $dumpvars(0, testbench);
end  
    
endmodule

out.vcd
$date
	Tue Dec 12 10:26:35 2023
$end
$version
	Icarus Verilog
$end
$timescale
	1ns
$end
$scope module testbench $end
$var wire 11 ! out [10:0] $end
$var wire 1 " input_grant $end
$var reg 1 # clk $end
$var reg 8 $ d [7:0] $end
$var reg 1 % rst $end
$scope module m1 $end
$var wire 1 # clk $end
$var wire 8 & d [7:0] $end
$var wire 1 % rst $end
$var reg 8 ' data [7:0] $end
$var reg 3 ( i [2:0] $end
$var reg 1 " input_grant $end
$var reg 11 ) out [10:0] $end
$upscope $end
$upscope $end
$enddefinitions $end
$comment Show the parameter values. $end
$dumpall
$end
#0
$dumpvars
b0 )
b0 (
bx '
bx &
0%
bx $
0#
0"
b0 !
$end
#5
1#
#10
1%
0#
#15
b1 (
1"
bx !
bx )
1#
#20
b10001111 $
b10001111 &
0#
#25
0"
b10 (
1#
#30
0#
#35
b11 (
1#
#40
0#
#45
b10001111 '
b0 (
1#
#50
0#
#55
b1 (
1"
b10001111 !
b10001111 )
1#
#60
0#
#65
b110101101 !
b110101101 )
0"
b10 (
1#
#70
0#
#75
b11 (
b1111101001 !
b1111101001 )
b111 $
b111 &
1#
#80
0#
#85
b10001111000 !
b10001111000 )
b111 '
b0 (
1#
#90
0#
#95
b1 (
1"
b111 !
b111 )
1#
#100
0#
#105
b10101 !
b10101 )
0"
b10 (
1#
#110
0#
#115
b11 (
b110001 !
b110001 )
1#
#120
0#
#125
b111000 !
b111000 )
b0 (
b110 $
b110 &
1#
#130
0#
#135
b1 (
1"
b110 '
b110 !
b110 )
b10000000 $
b10000000 &
1#
#140
0#
#145
b10010 !
b10010 )
0"
b10 (
b10000001 $
b10000001 &
1#
#150
0#
#155
b11 (
b101010 !
b101010 )
1#
#160
0#
#165
b110000 !
b110000 )
b10000001 '
b0 (
1#
#170
0#
#175
b1 (
1"
b10000001 !
b10000001 )
1#
#180
0#
#185
b110000011 !
b110000011 )
0"
b10 (
1#
#190
0#
#195
b11 (
b1110000111 !
b1110000111 )
1#
